gn_places/__init__.py
gn_places/admin.py
gn_places/apps.py
gn_places/config.py
gn_places/dal_urls.py
gn_places/dal_views.py
gn_places/import_utils.py
gn_places/models.py
gn_places/utils.py
gn_places/management/commands/import_ftc.py
gn_places/management/commands/import_places.py
gn_places/migrations/0001_initial.py
gn_places/migrations/__init__.py
gn_places/static/css/gn_places.css
gn_places/static/js/gn_places.js
gn_places/templates/gn_places/base.html
gn_places/test_utils/__init__.py
gn_places/test_utils/test_app/__init__.py
gn_places/test_utils/test_app/admin.py
gn_places/test_utils/test_app/apps.py
gn_places/test_utils/test_app/models.py
gn_places/test_utils/test_app/migrations/__init__.py
gn_places/tests/__init__.py
gn_places/tests/constants.py
gn_places/tests/test_for_utils.py
gn_places/tests/test_models.py
acdh_django_geonames-0.1.8.dist-info/AUTHORS.rst
acdh_django_geonames-0.1.8.dist-info/LICENSE
acdh_django_geonames-0.1.8.dist-info/METADATA
acdh_django_geonames-0.1.8.dist-info/WHEEL
acdh_django_geonames-0.1.8.dist-info/top_level.txt
acdh_django_geonames-0.1.8.dist-info/RECORD
