Metadata-Version: 2.1
Name: acdh-django-geonames
Version: 0.1.8
Summary: A django package providing models and views for Geoname Places
Home-page: https://github.com/acdh-oeaw/acdh-django-geonames
Author: Peter Andorfer
Author-email: peter.andorfer@oeaw.ac.at
License: MIT
Keywords: acdh-django-geonames
Platform: UNKNOWN
Classifier: Development Status :: 3 - Alpha
Classifier: Framework :: Django :: 3.1
Classifier: Intended Audience :: Developers
Classifier: License :: OSI Approved :: BSD License
Classifier: Natural Language :: English
Classifier: Programming Language :: Python :: 3.8
Requires-Dist: acdh-django-vocabs
Requires-Dist: acdh-geonames-utils (>=0.5)
Requires-Dist: tqdm
